chatora/confluent_kafka_ext/__init__.py
chatora/confluent_kafka_ext/_pkg_info.py
chatora/confluent_kafka_ext/api.py
chatora/confluent_kafka_ext/exception.py
chatora/confluent_kafka_ext/codec/__init__.py
chatora/confluent_kafka_ext/codec/api.py
chatora/confluent_kafka_ext/codec/avro_codec.py
chatora/confluent_kafka_ext/codec/base.py
chatora/confluent_kafka_ext/schema/__init__.py
chatora/confluent_kafka_ext/schema/api.py
chatora/confluent_kafka_ext/schema/base.py
chatora/confluent_kafka_ext/schema_registry/__init__.py
chatora/confluent_kafka_ext/schema_registry/api.py
chatora/confluent_kafka_ext/schema_registry/client.py
chatora/confluent_kafka_ext/schema_registry/subject_name_strategy.py
chatora.confluent_kafka_ext-0.4.dist-info/LICENSE.txt
chatora.confluent_kafka_ext-0.4.dist-info/METADATA
chatora.confluent_kafka_ext-0.4.dist-info/WHEEL
chatora.confluent_kafka_ext-0.4.dist-info/top_level.txt
chatora.confluent_kafka_ext-0.4.dist-info/zip-safe
chatora.confluent_kafka_ext-0.4.dist-info/RECORD
